deltarest/__init__.py
deltarest/rest.py
deltarest/service.py
deltarest-0.0.2.dist-info/LICENSE
deltarest-0.0.2.dist-info/METADATA
deltarest-0.0.2.dist-info/WHEEL
deltarest-0.0.2.dist-info/top_level.txt
deltarest-0.0.2.dist-info/RECORD
